asdfuzz/__init__.py
asdfuzz/__main__.py
asdfuzz/_utils.py
asdfuzz/app.py
asdfuzz/fuzzing/__init__.py
asdfuzz/fuzzing/fuzz_result.py
asdfuzz/fuzzing/fuzzer.py
asdfuzz/fuzzing/hex_replacements.py
asdfuzz/http/__init__.py
asdfuzz/http/cookie.py
asdfuzz/http/directory.py
asdfuzz/http/form_data.py
asdfuzz/http/json_data.py
asdfuzz/http/parameter.py
asdfuzz/http/request.py
asdfuzz/http/response.py
asdfuzz/http/url.py
asdfuzz/wordlists/__init__.py
asdfuzz/wordlists/default.txt
asdfuzz/wordlists/small.txt
asdfuzz-0.1.0.dist-info/LICENSE
asdfuzz-0.1.0.dist-info/METADATA
asdfuzz-0.1.0.dist-info/WHEEL
asdfuzz-0.1.0.dist-info/top_level.txt
asdfuzz-0.1.0.dist-info/RECORD
