Metadata-Version: 2.1
Name: asdfuzz
Version: 0.1.0
Summary: Web application fuzzer that automatically detects and fuzzes data in HTTP requests
Home-page: https://github.com/spmvg/asdfuzz
Author: Steven van Gemert
Author-email: steven@vangemert.dev
License: MIT
Classifier: Development Status :: 4 - Beta
Classifier: License :: OSI Approved :: MIT License
Classifier: Programming Language :: Python :: 3
Requires-Python: >=3.7
License-File: LICENSE
Requires-Dist: typer
Requires-Dist: keyboard
